<?xml version="1.0" encoding="utf-8" standalone="yes"?>
<Parameters>
  <Connection>
    <DeviceParameters>/IF=tcpip /LOPO=11159 /SA=1 </DeviceParameters>
    <ConnectionParameters>/COMT=2500 /RT=1000 /AM=* /SDT=5 /DAIP=192.168.200.50 /REPO=11159 /ANSL=1 /PT=11169 </ConnectionParameters>
  </Connection>
  <AsProject>
    <ApjFullFileName>C:\DataDistributionTest\DataDistributionTest\ControlPLC_DataDistribution.apj</ApjFullFileName>
    <ProjectName>ControlPLC_DataDistribution</ProjectName>
    <ActiveConfigurationName>ControlPLC_DataDistribution</ActiveConfigurationName>
    <LicenseDataFolder>C:\DataDistributionTest\DataDistributionTest\Temp\Objects\ControlPLC_DataDistribution\5PC900_TS17_02</LicenseDataFolder>
  </AsProject>
  <General>
    <DeleteParameterFile>false</DeleteParameterFile>
  </General>
</Parameters>